syllib/__init__.py
syllib/better_import.py
syllib/git/__init__.py
syllib/git/api.py
syllib/pip/__init__.py
syllib/tools/__init__.py
syllib/tools/api.py
syllib/xes/__init__.py
syllib/xes/api.py
syllib/xes/config.py
syllib/xes/msg.py
syllib-2022.110.120191336.dist-info/METADATA
syllib-2022.110.120191336.dist-info/WHEEL
syllib-2022.110.120191336.dist-info/top_level.txt
syllib-2022.110.120191336.dist-info/RECORD
