Metadata-Version: 2.1
Name: syllib
Version: 2022.110.120191336
Summary: suyiyi's package
Home-page: https://github.com/a-suyiyi/syllib
Author: suyiyi
Author-email: 3274719101@qq.com
License: UNKNOWN
Platform: UNKNOWN
Requires-Dist: requests
